rh_pre_commit/__init__.py
rh_pre_commit-0.0.0.dist-info/METADATA
rh_pre_commit-0.0.0.dist-info/WHEEL
rh_pre_commit-0.0.0.dist-info/RECORD
